{
  "date": "2026-03-19",
  "day": "Thursday",
  "display": "March 19, 2026",
  "generatedAt": "2026-04-14T05:22:15.858458",
  "summary": "0 terminal commands, 7 commits across 2 repos, 0 files modified.",
  "stats": {
    "commands": 0,
    "commits": 7,
    "repos": 2,
    "filesModified": 0
  },
  "categories": {},
  "activityByHour": {},
  "notableCommands": [],
  "gitActivity": [
    {
      "repo": "gma-design-system",
      "commits": [
        {
          "hash": "54666a7",
          "author": "Alek Manov",
          "message": "Initial commit",
          "time": "18:43"
        }
      ]
    },
    {
      "repo": "shadcnui",
      "commits": [
        {
          "hash": "563d572",
          "author": "github-actions[bot]",
          "message": "chore(release): version packages (#10120)",
          "time": "23:36"
        },
        {
          "hash": "687f098",
          "author": "shadcn",
          "message": "feat: chartColor and fontHeading (#10115)",
          "time": "23:35"
        },
        {
          "hash": "ebb900e",
          "author": "dependabot[bot]",
          "message": "chore(deps-dev): bump tailwindcss in /templates/react-router-app",
          "time": "16:23"
        },
        {
          "hash": "e2419f7",
          "author": "dependabot[bot]",
          "message": "chore(deps-dev): bump @tailwindcss/postcss in /templates/next-app",
          "time": "16:23"
        },
        {
          "hash": "1bb2382",
          "author": "dependabot[bot]",
          "message": "chore(deps-dev): bump jsdom in /templates/start-app",
          "time": "16:22"
        },
        {
          "hash": "57ec502",
          "author": "dependabot[bot]",
          "message": "chore(deps): bump tailwindcss in /templates/start-app",
          "time": "16:22"
        }
      ]
    }
  ],
  "fileGroups": {}
}